README.md
esl_s3.py
setup.py
esl_s3.egg-info/PKG-INFO
esl_s3.egg-info/SOURCES.txt
esl_s3.egg-info/dependency_links.txt
esl_s3.egg-info/entry_points.txt
esl_s3.egg-info/requires.txt
esl_s3.egg-info/top_level.txt